s3parq/__init__.py
s3parq/fetch_parq.py
s3parq/publish_parq.py
s3parq/publish_redshift.py
s3parq/s3_naming_helper.py
s3parq/session_helper.py
s3parq/testing_helper.py
s3parq-2.1.17.dist-info/LICENSE
s3parq-2.1.17.dist-info/METADATA
s3parq-2.1.17.dist-info/WHEEL
s3parq-2.1.17.dist-info/top_level.txt
s3parq-2.1.17.dist-info/RECORD
