Metadata-Version: 2.1
Name: s3parq
Version: 2.1.17
Summary: Write and read/query s3 parquet data using Athena/Spectrum/Hive style partitioning.
Home-page: https://github.com/IntegriChain1/s3parq
Author: Integrichain Innovation Team
Author-email: engineering@integrichain.com
License: MIT
Platform: UNKNOWN
Classifier: License :: OSI Approved :: MIT License
Classifier: Programming Language :: Python :: 3
Classifier: Programming Language :: Python :: 3.7
Requires-Dist: pandas <1,>=0.24.2
Requires-Dist: pyarrow >=0.13.0
Requires-Dist: boto3 >=1.9
Requires-Dist: s3fs >=0.2
Requires-Dist: psycopg2 ==2.8.3
Requires-Dist: SQLAlchemy >=1.3
